[
    {
        "id": 1,
        "time": "2019.4.4",
        "type": "咨询",
        "content": "你好,我想查一下我医保卡消费的明细，怎么查？"
    },
    {
        "id": 2,
        "time": "2019.4.5",
        "type": "咨询",
        "content": "你好，我是新到桐庐工作的一名研究生，想请问下咱们桐庐体育******是否开放，我想坚持锻炼下，现在只查到各个球类场馆的开放信息，所以想咨询一下，谢谢"
    },
    {
        "id": 3,
        "time": "2019.4.5",
        "type": "建议",
        "content": "方便师生、居民出行，也******客流量。同时希望双向对开"
    },
    {
        "id": 4,
        "time": "2019.4.3",
        "type": "投诉",
        "content": "杭州一桶金服务有限公司合同诈骗假标自融，******金融办不作为，成立的委员会也被控股人吴新军维稳"
    },
    {
        "id": 5,
        "time": "2019.4.6",
        "type": "无效信息",
        "content": "我有个罚款1000元"
    },
    {
        "id": 6,
        "time": "2019.4.6",
        "type": "建议",
        "content": "如题，火车东站的非机动车停车场地太少了！建议增加更多的地方停放"
    },
    {
        "id": 7,
        "time": "2019.4.7",
        "type": "投诉",
        "content": "******一直在拖文明杭州建设的后腿，每天在和谐嘉园门口有大量非法电动车摩的聚集，拉客载客，在周边逆行，超速，骑车带人，闯红灯，全杭州哪个区有电动车摩的的？"
    },
    {
        "id": 8,
        "time": "2019.4.8",
        "type": "询问",
        "content": "生育建档,流程，需要材料，去哪里办理"
    },
    {
        "id": 9,
        "time": "2019.4.8",
        "type": "询问",
        "content": "你好，2018年11月份的主治医师聘用申请什么时候能够批准下来？"
    },
    {
        "id": 10,
        "time": "2019.4.8",
        "type": "投诉",
        "content": "12点30坐湘湖到临平地铁，上面广告声音太吵了"
    }
]
